LICENSE
README.md
seabird/__init__.py
seabird/common.py
seabird/seabird.py
python_seabird-0.1.1.dist-info/LICENSE
python_seabird-0.1.1.dist-info/WHEEL
python_seabird-0.1.1.dist-info/METADATA
python_seabird-0.1.1.dist-info/RECORD
