Metadata-Version: 2.1
Name: python-seabird
Version: 0.1.1
Summary: 
License: MIT
Author: Kaleb Elwert
Author-email: belak@coded.io
Requires-Python: >=3.6,<4.0
Classifier: License :: OSI Approved :: MIT License
Classifier: Programming Language :: Python :: 3
Classifier: Programming Language :: Python :: 3.6
Classifier: Programming Language :: Python :: 3.7
Classifier: Programming Language :: Python :: 3.8
Classifier: Programming Language :: Python :: 3.9
Requires-Dist: betterproto (>=1.2.5,<2.0.0)
Requires-Dist: grpclib (>=0.4.1,<0.5.0)
